pixelle/.dockerignore
pixelle/.gitignore
pixelle/Dockerfile
pixelle/__init__.py
pixelle/cli.py
pixelle/logger.py
pixelle/main.py
pixelle/mcp_core.py
pixelle/settings.py
pixelle/.chainlit/config.toml
pixelle/.chainlit/translations/bn.json
pixelle/.chainlit/translations/el-GR.json
pixelle/.chainlit/translations/en-US.json
pixelle/.chainlit/translations/fr-FR.json
pixelle/.chainlit/translations/gu.json
pixelle/.chainlit/translations/he-IL.json
pixelle/.chainlit/translations/hi.json
pixelle/.chainlit/translations/ja.json
pixelle/.chainlit/translations/kn.json
pixelle/.chainlit/translations/ml.json
pixelle/.chainlit/translations/mr.json
pixelle/.chainlit/translations/nl.json
pixelle/.chainlit/translations/ta.json
pixelle/.chainlit/translations/te.json
pixelle/.chainlit/translations/zh-CN.json
pixelle/api/__init__.py
pixelle/api/files_api.py
pixelle/comfyui/__init__.py
pixelle/comfyui/base_executor.py
pixelle/comfyui/facade.py
pixelle/comfyui/http_executor.py
pixelle/comfyui/models.py
pixelle/comfyui/websocket_executor.py
pixelle/comfyui/workflow_parser.py
pixelle/manager/__init__.py
pixelle/manager/workflow_manager.py
pixelle/public/app.css
pixelle/public/app.js
pixelle/public/catalog.svg
pixelle/public/favicon.png
pixelle/public/github.svg
pixelle/public/login_background.png
pixelle/public/logo_dark.png
pixelle/public/logo_light.png
pixelle/public/theme.json
pixelle/public/tool.svg
pixelle/public/elements/AlertDialog.jsx
pixelle/public/elements/PromptDialog.jsx
pixelle/starters/__init__.py
pixelle/tools/__init__.py
pixelle/tools/file_uploader_tool.py
pixelle/tools/i_crop.py
pixelle/tools/workflow_manager_tool.py
pixelle/upload/__init__.py
pixelle/upload/base.py
pixelle/upload/file_service.py
pixelle/upload/local_storage.py
pixelle/utils/__init__.py
pixelle/utils/config_util.py
pixelle/utils/dynamic_util.py
pixelle/utils/file_uploader.py
pixelle/utils/file_util.py
pixelle/utils/image_util.py
pixelle/utils/network_util.py
pixelle/utils/os_util.py
pixelle_mcp-0.1.3.dist-info/METADATA
pixelle_mcp-0.1.3.dist-info/WHEEL
pixelle_mcp-0.1.3.dist-info/entry_points.txt
pixelle_mcp-0.1.3.dist-info/licenses/LICENSE
pixelle_mcp-0.1.3.dist-info/licenses/NOTICE
pixelle_mcp-0.1.3.dist-info/RECORD
