Metadata-Version: 2.4
Name: pixelle-mcp
Version: 0.1.3
Summary: Pixelle MCP: Convert ComfyUI workflows into MCP Tools with a single command, providing an MCP server and a Chainlit-based web UI.
Project-URL: Homepage, https://pixelle.ai
Project-URL: Repository, https://github.com/AIDC-AI/Pixelle-MCP
Project-URL: Issues, https://github.com/AIDC-AI/Pixelle-MCP/issues
Author: AIDC-AI
License: MIT
License-File: LICENSE
License-File: NOTICE
Keywords: AIGC,Chainlit,ComfyUI,LLM,MCP
Classifier: Intended Audience :: Developers
Classifier: License :: OSI Approved :: MIT License
Classifier: Operating System :: OS Independent
Classifier: Programming Language :: Python :: 3
Classifier: Programming Language :: Python :: 3 :: Only
Classifier: Programming Language :: Python :: 3.11
Classifier: Topic :: Software Development :: Libraries :: Application Frameworks
Requires-Python: >=3.11
Requires-Dist: aiofiles>=24.1.0
Requires-Dist: aiohttp>=3.9.0
Requires-Dist: boto3>=1.38.34
Requires-Dist: chainlit>=2.7.1.1
Requires-Dist: fastapi>=0.116.1
Requires-Dist: fastmcp>=2.7.1
Requires-Dist: litellm>=1.76.0
Requires-Dist: pillow>=11.2.1
Requires-Dist: psutil>=5.9.0
Requires-Dist: python-dotenv>=1.1.1
Requires-Dist: questionary>=2.0.0
Requires-Dist: requests>=2.32.3
Requires-Dist: rich>=13.0.0
Requires-Dist: typer>=0.12.0
Requires-Dist: websockets>=12.0
